{
  "id": "D96_FileManagerDensityComposition",
  "size": [
    520,
    340
  ],
  "font": {
    "path": "standardtest/fonts/DejaVuSans.ttf",
    "size": 11
  },
  "ops": [
    {
      "op": "clear",
      "rgba": [
        1,
        1,
        1,
        1
      ]
    },
    {
      "op": "fill_rect",
      "rect": [
        0,
        0,
        520,
        340
      ],
      "rgba": [
        1,
        1,
        1,
        1
      ]
    },
    {
      "op": "fill_rect",
      "rect": [
        0,
        0,
        520,
        36
      ],
      "rgba": [
        0.94,
        0.95,
        0.97,
        1
      ]
    },
    {
      "op": "fill_text",
      "rgba": [
        0.2,
        0.45,
        0.9,
        1
      ],
      "text": "/home/user/projects/gpui/render",
      "x": 12,
      "y": 24
    },
    {
      "op": "clip_rect",
      "rect": [
        0,
        36,
        160,
        304
      ]
    },
    {
      "op": "fill_rect",
      "rect": [
        0,
        36,
        160,
        304
      ],
      "rgba": [
        0.97,
        0.97,
        0.98,
        1
      ]
    },
    {
      "op": "fill_text",
      "rgba": [
        0.2,
        0.22,
        0.26,
        1
      ],
      "text": "folder-00",
      "x": 12,
      "y": 60
    },
    {
      "op": "fill_text",
      "rgba": [
        0.2,
        0.22,
        0.26,
        1
      ],
      "text": " folder-01",
      "x": 12,
      "y": 82
    },
    {
      "op": "fill_text",
      "rgba": [
        0.2,
        0.22,
        0.26,
        1
      ],
      "text": "  folder-02",
      "x": 12,
      "y": 104
    },
    {
      "op": "fill_text",
      "rgba": [
        0.2,
        0.22,
        0.26,
        1
      ],
      "text": "folder-03",
      "x": 12,
      "y": 126
    },
    {
      "op": "fill_rect",
      "rect": [
        0,
        134,
        160,
        22
      ],
      "rgba": [
        0.85,
        0.91,
        1,
        1
      ]
    },
    {
      "op": "fill_text",
      "rgba": [
        0.2,
        0.22,
        0.26,
        1
      ],
      "text": " folder-04",
      "x": 12,
      "y": 148
    },
    {
      "op": "fill_text",
      "rgba": [
        0.2,
        0.22,
        0.26,
        1
      ],
      "text": "  folder-05",
      "x": 12,
      "y": 170
    },
    {
      "op": "fill_text",
      "rgba": [
        0.2,
        0.22,
        0.26,
        1
      ],
      "text": "folder-06",
      "x": 12,
      "y": 192
    },
    {
      "op": "fill_text",
      "rgba": [
        0.2,
        0.22,
        0.26,
        1
      ],
      "text": " folder-07",
      "x": 12,
      "y": 214
    },
    {
      "op": "fill_text",
      "rgba": [
        0.2,
        0.22,
        0.26,
        1
      ],
      "text": "  folder-08",
      "x": 12,
      "y": 236
    },
    {
      "op": "fill_text",
      "rgba": [
        0.2,
        0.22,
        0.26,
        1
      ],
      "text": "folder-09",
      "x": 12,
      "y": 258
    },
    {
      "op": "fill_text",
      "rgba": [
        0.2,
        0.22,
        0.26,
        1
      ],
      "text": " folder-10",
      "x": 12,
      "y": 280
    },
    {
      "op": "fill_text",
      "rgba": [
        0.2,
        0.22,
        0.26,
        1
      ],
      "text": "  folder-11",
      "x": 12,
      "y": 302
    },
    {
      "op": "reset_clip"
    },
    {
      "op": "clip_rect",
      "rect": [
        160,
        36,
        360,
        304
      ]
    },
    {
      "op": "fill_rect",
      "rect": [
        160,
        36,
        360,
        304
      ],
      "rgba": [
        1,
        1,
        1,
        1
      ]
    },
    {
      "op": "push"
    },
    {
      "close": true,
      "op": "clip_path",
      "points": [
        [
          186,
          56
        ],
        [
          206,
          56
        ],
        [
          212,
          82
        ],
        [
          186,
          88
        ],
        [
          180,
          62
        ]
      ]
    },
    {
      "img_h": 32,
      "img_w": 32,
      "op": "draw_image_solid",
      "rgba": [
        0.23529411764705882,
        0.5490196078431373,
        0.8627450980392157,
        1
      ],
      "x": 180,
      "y": 56
    },
    {
      "op": "pop"
    },
    {
      "op": "fill_text",
      "rgba": [
        0.25,
        0.27,
        0.32,
        1
      ],
      "text": "f0",
      "x": 184,
      "y": 104
    },
    {
      "op": "push"
    },
    {
      "close": true,
      "op": "clip_path",
      "points": [
        [
          250,
          56
        ],
        [
          270,
          56
        ],
        [
          276,
          82
        ],
        [
          250,
          88
        ],
        [
          244,
          62
        ]
      ]
    },
    {
      "img_h": 32,
      "img_w": 32,
      "op": "draw_image_solid",
      "rgba": [
        0.23529411764705882,
        0.5490196078431373,
        0.8627450980392157,
        1
      ],
      "x": 244,
      "y": 56
    },
    {
      "op": "pop"
    },
    {
      "op": "fill_text",
      "rgba": [
        0.25,
        0.27,
        0.32,
        1
      ],
      "text": "f1",
      "x": 248,
      "y": 104
    },
    {
      "op": "push"
    },
    {
      "close": true,
      "op": "clip_path",
      "points": [
        [
          314,
          56
        ],
        [
          334,
          56
        ],
        [
          340,
          82
        ],
        [
          314,
          88
        ],
        [
          308,
          62
        ]
      ]
    },
    {
      "img_h": 32,
      "img_w": 32,
      "op": "draw_image_solid",
      "rgba": [
        0.23529411764705882,
        0.5490196078431373,
        0.8627450980392157,
        1
      ],
      "x": 308,
      "y": 56
    },
    {
      "op": "pop"
    },
    {
      "op": "fill_text",
      "rgba": [
        0.25,
        0.27,
        0.32,
        1
      ],
      "text": "f2",
      "x": 312,
      "y": 104
    },
    {
      "op": "push"
    },
    {
      "close": true,
      "op": "clip_path",
      "points": [
        [
          378,
          56
        ],
        [
          398,
          56
        ],
        [
          404,
          82
        ],
        [
          378,
          88
        ],
        [
          372,
          62
        ]
      ]
    },
    {
      "img_h": 32,
      "img_w": 32,
      "op": "draw_image_solid",
      "rgba": [
        0.23529411764705882,
        0.5490196078431373,
        0.8627450980392157,
        1
      ],
      "x": 372,
      "y": 56
    },
    {
      "op": "pop"
    },
    {
      "op": "fill_text",
      "rgba": [
        0.25,
        0.27,
        0.32,
        1
      ],
      "text": "f3",
      "x": 376,
      "y": 104
    },
    {
      "op": "push"
    },
    {
      "close": true,
      "op": "clip_path",
      "points": [
        [
          442,
          56
        ],
        [
          462,
          56
        ],
        [
          468,
          82
        ],
        [
          442,
          88
        ],
        [
          436,
          62
        ]
      ]
    },
    {
      "img_h": 32,
      "img_w": 32,
      "op": "draw_image_solid",
      "rgba": [
        0.23529411764705882,
        0.5490196078431373,
        0.8627450980392157,
        1
      ],
      "x": 436,
      "y": 56
    },
    {
      "op": "pop"
    },
    {
      "op": "fill_text",
      "rgba": [
        0.25,
        0.27,
        0.32,
        1
      ],
      "text": "f4",
      "x": 440,
      "y": 104
    },
    {
      "op": "push"
    },
    {
      "close": true,
      "op": "clip_path",
      "points": [
        [
          186,
          120
        ],
        [
          206,
          120
        ],
        [
          212,
          146
        ],
        [
          186,
          152
        ],
        [
          180,
          126
        ]
      ]
    },
    {
      "img_h": 32,
      "img_w": 32,
      "op": "draw_image_solid",
      "rgba": [
        0.23529411764705882,
        0.5490196078431373,
        0.8627450980392157,
        1
      ],
      "x": 180,
      "y": 120
    },
    {
      "op": "pop"
    },
    {
      "op": "fill_text",
      "rgba": [
        0.25,
        0.27,
        0.32,
        1
      ],
      "text": "f5",
      "x": 184,
      "y": 168
    },
    {
      "op": "push"
    },
    {
      "close": true,
      "op": "clip_path",
      "points": [
        [
          250,
          120
        ],
        [
          270,
          120
        ],
        [
          276,
          146
        ],
        [
          250,
          152
        ],
        [
          244,
          126
        ]
      ]
    },
    {
      "img_h": 32,
      "img_w": 32,
      "op": "draw_image_solid",
      "rgba": [
        0.23529411764705882,
        0.5490196078431373,
        0.8627450980392157,
        1
      ],
      "x": 244,
      "y": 120
    },
    {
      "op": "pop"
    },
    {
      "op": "fill_text",
      "rgba": [
        0.25,
        0.27,
        0.32,
        1
      ],
      "text": "f6",
      "x": 248,
      "y": 168
    },
    {
      "blend": "normal",
      "op": "layer_begin",
      "opacity": 1
    },
    {
      "op": "fill_rrect",
      "radius": 8,
      "rect": [
        302,
        114,
        56,
        56
      ],
      "rgba": [
        0.88,
        0.93,
        1,
        1
      ]
    },
    {
      "op": "layer_end"
    },
    {
      "op": "push"
    },
    {
      "close": true,
      "op": "clip_path",
      "points": [
        [
          314,
          120
        ],
        [
          334,
          120
        ],
        [
          340,
          146
        ],
        [
          314,
          152
        ],
        [
          308,
          126
        ]
      ]
    },
    {
      "img_h": 32,
      "img_w": 32,
      "op": "draw_image_solid",
      "rgba": [
        0.23529411764705882,
        0.5490196078431373,
        0.8627450980392157,
        1
      ],
      "x": 308,
      "y": 120
    },
    {
      "op": "pop"
    },
    {
      "op": "fill_text",
      "rgba": [
        0.25,
        0.27,
        0.32,
        1
      ],
      "text": "f7",
      "x": 312,
      "y": 168
    },
    {
      "op": "push"
    },
    {
      "close": true,
      "op": "clip_path",
      "points": [
        [
          378,
          120
        ],
        [
          398,
          120
        ],
        [
          404,
          146
        ],
        [
          378,
          152
        ],
        [
          372,
          126
        ]
      ]
    },
    {
      "img_h": 32,
      "img_w": 32,
      "op": "draw_image_solid",
      "rgba": [
        0.23529411764705882,
        0.5490196078431373,
        0.8627450980392157,
        1
      ],
      "x": 372,
      "y": 120
    },
    {
      "op": "pop"
    },
    {
      "op": "fill_text",
      "rgba": [
        0.25,
        0.27,
        0.32,
        1
      ],
      "text": "f8",
      "x": 376,
      "y": 168
    },
    {
      "op": "push"
    },
    {
      "close": true,
      "op": "clip_path",
      "points": [
        [
          442,
          120
        ],
        [
          462,
          120
        ],
        [
          468,
          146
        ],
        [
          442,
          152
        ],
        [
          436,
          126
        ]
      ]
    },
    {
      "img_h": 32,
      "img_w": 32,
      "op": "draw_image_solid",
      "rgba": [
        0.23529411764705882,
        0.5490196078431373,
        0.8627450980392157,
        1
      ],
      "x": 436,
      "y": 120
    },
    {
      "op": "pop"
    },
    {
      "op": "fill_text",
      "rgba": [
        0.25,
        0.27,
        0.32,
        1
      ],
      "text": "f9",
      "x": 440,
      "y": 168
    },
    {
      "op": "push"
    },
    {
      "close": true,
      "op": "clip_path",
      "points": [
        [
          186,
          184
        ],
        [
          206,
          184
        ],
        [
          212,
          210
        ],
        [
          186,
          216
        ],
        [
          180,
          190
        ]
      ]
    },
    {
      "img_h": 32,
      "img_w": 32,
      "op": "draw_image_solid",
      "rgba": [
        0.23529411764705882,
        0.5490196078431373,
        0.8627450980392157,
        1
      ],
      "x": 180,
      "y": 184
    },
    {
      "op": "pop"
    },
    {
      "op": "fill_text",
      "rgba": [
        0.25,
        0.27,
        0.32,
        1
      ],
      "text": "f10",
      "x": 184,
      "y": 232
    },
    {
      "op": "push"
    },
    {
      "close": true,
      "op": "clip_path",
      "points": [
        [
          250,
          184
        ],
        [
          270,
          184
        ],
        [
          276,
          210
        ],
        [
          250,
          216
        ],
        [
          244,
          190
        ]
      ]
    },
    {
      "img_h": 32,
      "img_w": 32,
      "op": "draw_image_solid",
      "rgba": [
        0.23529411764705882,
        0.5490196078431373,
        0.8627450980392157,
        1
      ],
      "x": 244,
      "y": 184
    },
    {
      "op": "pop"
    },
    {
      "op": "fill_text",
      "rgba": [
        0.25,
        0.27,
        0.32,
        1
      ],
      "text": "f11",
      "x": 248,
      "y": 232
    },
    {
      "op": "push"
    },
    {
      "close": true,
      "op": "clip_path",
      "points": [
        [
          314,
          184
        ],
        [
          334,
          184
        ],
        [
          340,
          210
        ],
        [
          314,
          216
        ],
        [
          308,
          190
        ]
      ]
    },
    {
      "img_h": 32,
      "img_w": 32,
      "op": "draw_image_solid",
      "rgba": [
        0.23529411764705882,
        0.5490196078431373,
        0.8627450980392157,
        1
      ],
      "x": 308,
      "y": 184
    },
    {
      "op": "pop"
    },
    {
      "op": "fill_text",
      "rgba": [
        0.25,
        0.27,
        0.32,
        1
      ],
      "text": "f12",
      "x": 312,
      "y": 232
    },
    {
      "op": "push"
    },
    {
      "close": true,
      "op": "clip_path",
      "points": [
        [
          378,
          184
        ],
        [
          398,
          184
        ],
        [
          404,
          210
        ],
        [
          378,
          216
        ],
        [
          372,
          190
        ]
      ]
    },
    {
      "img_h": 32,
      "img_w": 32,
      "op": "draw_image_solid",
      "rgba": [
        0.23529411764705882,
        0.5490196078431373,
        0.8627450980392157,
        1
      ],
      "x": 372,
      "y": 184
    },
    {
      "op": "pop"
    },
    {
      "op": "fill_text",
      "rgba": [
        0.25,
        0.27,
        0.32,
        1
      ],
      "text": "f13",
      "x": 376,
      "y": 232
    },
    {
      "op": "push"
    },
    {
      "close": true,
      "op": "clip_path",
      "points": [
        [
          442,
          184
        ],
        [
          462,
          184
        ],
        [
          468,
          210
        ],
        [
          442,
          216
        ],
        [
          436,
          190
        ]
      ]
    },
    {
      "img_h": 32,
      "img_w": 32,
      "op": "draw_image_solid",
      "rgba": [
        0.23529411764705882,
        0.5490196078431373,
        0.8627450980392157,
        1
      ],
      "x": 436,
      "y": 184
    },
    {
      "op": "pop"
    },
    {
      "op": "fill_text",
      "rgba": [
        0.25,
        0.27,
        0.32,
        1
      ],
      "text": "f14",
      "x": 440,
      "y": 232
    },
    {
      "op": "push"
    },
    {
      "close": true,
      "op": "clip_path",
      "points": [
        [
          186,
          248
        ],
        [
          206,
          248
        ],
        [
          212,
          274
        ],
        [
          186,
          280
        ],
        [
          180,
          254
        ]
      ]
    },
    {
      "img_h": 32,
      "img_w": 32,
      "op": "draw_image_solid",
      "rgba": [
        0.23529411764705882,
        0.5490196078431373,
        0.8627450980392157,
        1
      ],
      "x": 180,
      "y": 248
    },
    {
      "op": "pop"
    },
    {
      "op": "fill_text",
      "rgba": [
        0.25,
        0.27,
        0.32,
        1
      ],
      "text": "f15",
      "x": 184,
      "y": 296
    },
    {
      "op": "push"
    },
    {
      "close": true,
      "op": "clip_path",
      "points": [
        [
          250,
          248
        ],
        [
          270,
          248
        ],
        [
          276,
          274
        ],
        [
          250,
          280
        ],
        [
          244,
          254
        ]
      ]
    },
    {
      "img_h": 32,
      "img_w": 32,
      "op": "draw_image_solid",
      "rgba": [
        0.23529411764705882,
        0.5490196078431373,
        0.8627450980392157,
        1
      ],
      "x": 244,
      "y": 248
    },
    {
      "op": "pop"
    },
    {
      "op": "fill_text",
      "rgba": [
        0.25,
        0.27,
        0.32,
        1
      ],
      "text": "f16",
      "x": 248,
      "y": 296
    },
    {
      "op": "push"
    },
    {
      "close": true,
      "op": "clip_path",
      "points": [
        [
          314,
          248
        ],
        [
          334,
          248
        ],
        [
          340,
          274
        ],
        [
          314,
          280
        ],
        [
          308,
          254
        ]
      ]
    },
    {
      "img_h": 32,
      "img_w": 32,
      "op": "draw_image_solid",
      "rgba": [
        0.23529411764705882,
        0.5490196078431373,
        0.8627450980392157,
        1
      ],
      "x": 308,
      "y": 248
    },
    {
      "op": "pop"
    },
    {
      "op": "fill_text",
      "rgba": [
        0.25,
        0.27,
        0.32,
        1
      ],
      "text": "f17",
      "x": 312,
      "y": 296
    },
    {
      "op": "push"
    },
    {
      "close": true,
      "op": "clip_path",
      "points": [
        [
          378,
          248
        ],
        [
          398,
          248
        ],
        [
          404,
          274
        ],
        [
          378,
          280
        ],
        [
          372,
          254
        ]
      ]
    },
    {
      "img_h": 32,
      "img_w": 32,
      "op": "draw_image_solid",
      "rgba": [
        0.23529411764705882,
        0.5490196078431373,
        0.8627450980392157,
        1
      ],
      "x": 372,
      "y": 248
    },
    {
      "op": "pop"
    },
    {
      "op": "fill_text",
      "rgba": [
        0.25,
        0.27,
        0.32,
        1
      ],
      "text": "f18",
      "x": 376,
      "y": 296
    },
    {
      "op": "push"
    },
    {
      "close": true,
      "op": "clip_path",
      "points": [
        [
          442,
          248
        ],
        [
          462,
          248
        ],
        [
          468,
          274
        ],
        [
          442,
          280
        ],
        [
          436,
          254
        ]
      ]
    },
    {
      "img_h": 32,
      "img_w": 32,
      "op": "draw_image_solid",
      "rgba": [
        0.23529411764705882,
        0.5490196078431373,
        0.8627450980392157,
        1
      ],
      "x": 436,
      "y": 248
    },
    {
      "op": "pop"
    },
    {
      "op": "fill_text",
      "rgba": [
        0.25,
        0.27,
        0.32,
        1
      ],
      "text": "f19",
      "x": 440,
      "y": 296
    },
    {
      "op": "reset_clip"
    }
  ],
  "note": "auto-recorded from Go composition test (GPUI_RECORD_SCENES=1)"
}
